README.txt
ez_setup.py
setup.py
whs.utils.rwlock.egg-info/PKG-INFO
whs.utils.rwlock.egg-info/SOURCES.txt
whs.utils.rwlock.egg-info/dependency_links.txt
whs.utils.rwlock.egg-info/namespace_packages.txt
whs.utils.rwlock.egg-info/top_level.txt
whs/utils/rwlock/__init__.py
whs/utils/rwlock/testing.py
whs/utils/rwlock/testing_with_context.py