Metadata-Version: 1.1
Name: whs.utils.rwlock
Version: 0.6.0
Summary: This is specific kind of lock, that allows only one operation at the time (read or write) by any number of callers.
Home-page: devzone.itadmin.pl
Author: Filip Malczak
Author-email: filip(dot)malczak(at)gmail(dot)com
License: BSD license (http://opensource.org/licenses/bsd-license.php); owner: Web Harvesting Solutions Ltd; year: 2013
Platform: Any
Classifier: Development Status :: 4 - Beta
Classifier: Intended Audience :: Developers
Classifier: License :: OSI Approved :: BSD License
Classifier: Natural Language :: English
Classifier: Operating System :: OS Independent
Classifier: Programming Language :: Python :: 3
Classifier: Topic :: Utilities
